aerialog/__init__.py
aerialog/colours.py
aerialog/logger.py
aerialog-0.0.3.dist-info/LICENSE
aerialog-0.0.3.dist-info/METADATA
aerialog-0.0.3.dist-info/WHEEL
aerialog-0.0.3.dist-info/top_level.txt
aerialog-0.0.3.dist-info/RECORD
