Metadata-Version: 2.1
Name: aerialog
Version: 0.0.3
Summary: A simple logger for python, but with colours!
Author-email: tomos <oerushia@gmail.com>
Project-URL: Homepage, https://github.com/devtomos/aerialog
Project-URL: Issues, https://github.com/devtomos/aerialog/issues
Classifier: Development Status :: 3 - Alpha
Classifier: Programming Language :: Python :: 3.8
Classifier: License :: OSI Approved :: MIT License
Classifier: Operating System :: OS Independent
Requires-Python: >=3.8
License-File: LICENSE
Requires-Dist: python-dotenv
